ya/__init__.py
ya/resourcepool.py
ya.resourcepool-0.1.1.dist-info/LICENSE
ya.resourcepool-0.1.1.dist-info/METADATA
ya.resourcepool-0.1.1.dist-info/WHEEL
ya.resourcepool-0.1.1.dist-info/top_level.txt
ya.resourcepool-0.1.1.dist-info/RECORD
