Metadata-Version: 2.1
Name: ya.resourcepool
Version: 0.1.1
Summary: Resource management for Python objects
Home-page: https://github.com/knowikow/ya.resourcepool.py
License: UNKNOWN
Platform: UNKNOWN
Classifier: Development Status :: 4 - Beta
Classifier: Intended Audience :: Developers
Classifier: License :: OSI Approved :: MIT License
Classifier: Operating System :: OS Independent
Classifier: Programming Language :: Python :: 3
Classifier: Topic :: Software Development :: Libraries :: Python Modules
Requires-Python: >=3.7
Provides-Extra: dev
Requires-Dist: mutmut ; extra == 'dev'
Provides-Extra: testing
Requires-Dist: pytest ; extra == 'testing'
Requires-Dist: pytest-cov ; extra == 'testing'
Requires-Dist: flake8 ; extra == 'testing'
Requires-Dist: flake8-annotations ; extra == 'testing'
Requires-Dist: flake8-comprehensions ; extra == 'testing'
Requires-Dist: flake8-docstrings ; extra == 'testing'
Requires-Dist: flake8-isort ; extra == 'testing'
Requires-Dist: flake8-raise ; extra == 'testing'
Requires-Dist: flake8-typing-imports ; extra == 'testing'
